xy_console/Console.py
xy_console/ModuleData.py
xy_console/Resource.py
xy_console/__init__.py
xy_console/utils.py
xy_console/execute/Main.py
xy_console/execute/__init__.py
xy_console-1.0.6.dist-info/LICENSE
xy_console-1.0.6.dist-info/METADATA
xy_console-1.0.6.dist-info/WHEEL
xy_console-1.0.6.dist-info/top_level.txt
xy_console-1.0.6.dist-info/RECORD
