Metadata-Version: 2.1
Name: xy_console
Version: 1.0.6
Summary: xy_console 模块
Author-email: 余洋 <yuyangit.0515@qq.com>
Classifier: Programming Language :: Python :: 3.8
Requires-Python: >=3.8
License-File: LICENSE
Requires-Dist: rich
